<annotation>
	<folder>plates</folder>
	<filename>100.jpg</filename>
	<path>E:\Islamabad Number Plates\plates\100.jpg</path>
	<source>
		<database>Unknown</database>
	</source>
	<size>
		<width>1024</width>
		<height>617</height>
		<depth>3</depth>
	</size>
	<segmented>0</segmented>
	<object>
		<name>plate</name>
		<pose>Unspecified</pose>
		<truncated>0</truncated>
		<difficult>0</difficult>
		<bndbox>
			<xmin>13</xmin>
			<ymin>12</ymin>
			<xmax>1014</xmax>
			<ymax>605</ymax>
		</bndbox>
	</object>
</annotation>
